<?xml version="1.0" encoding="UTF-8"?>
<build-type xmlns:xsi="http://www.w3.org/2001/XMLSchema-instance" uuid="46b6ab60-30cd-48e0-a3c9-9645ca1a3f84" xsi:noNamespaceSchemaLocation="http://www.jetbrains.com/teamcity/schemas/2017.2/project-config.xsd">
  <name>TestConfig</name>
  <description />
  <settings>
    <parameters />
    <build-runners />
    <vcs-settings>
      <vcs-entry-ref root-id="KotlinBuildProject_Kotlinroot" />
    </vcs-settings>
    <requirements />
    <build-triggers />
    <cleanup />
  </settings>
</build-type>

